src/app.py
terraform_plan_summary-1.0.2.dist-info/METADATA
terraform_plan_summary-1.0.2.dist-info/WHEEL
terraform_plan_summary-1.0.2.dist-info/entry_points.txt
terraform_plan_summary-1.0.2.dist-info/licenses/LICENSE
terraform_plan_summary-1.0.2.dist-info/RECORD
